jertl/.DS_Store
jertl/__about__.py
jertl/__init__.py
jertl/exceptions.py
jertl/processors.py
jertl/requirements.txt
jertl/results.py
jertl/ast/.DS_Store
jertl/ast/builder.py
jertl/ast/emitter.py
jertl/ast/helpers.py
jertl/ast/representation.py
jertl/engine/.DS_Store
jertl/engine/construct.py
jertl/engine/interpreter.py
jertl/engine/masks.py
jertl/engine/opcodes.py
jertl/parser/.DS_Store
jertl/parser/Jertl.g4
jertl/parser/Jertl.interp
jertl/parser/Jertl.tokens
jertl/parser/JertlLexer.interp
jertl/parser/JertlLexer.py
jertl/parser/JertlLexer.tokens
jertl/parser/JertlListener.py
jertl/parser/JertlParser.py
jertl/parser/__init__.py
jertl-0.1.3.dist-info/METADATA
jertl-0.1.3.dist-info/WHEEL
jertl-0.1.3.dist-info/entry_points.txt
jertl-0.1.3.dist-info/license_files/LICENSE.txt
jertl-0.1.3.dist-info/RECORD
