Metadata-Version: 2.1
Name: jertl
Version: 0.1.3
Summary: A minimum viable package for processing structured data
Project-URL: Documentation, https://jertl.readthedocs.io/en/latest/
Project-URL: Issues, https://github.com/RaymondPelletier/jertl/issues
Project-URL: Source, https://github.com/RaymondPelletier/jertl
Author-email: Ray Pelletier <68929475+RaymondPelletier@users.noreply.github.com>
Keywords: JSON,development,pattern matching,structured data
Classifier: Development Status :: 3 - Alpha
Classifier: Intended Audience :: Developers
Classifier: License :: OSI Approved :: Apache Software License
Classifier: Programming Language :: Other
Classifier: Programming Language :: Python
Classifier: Programming Language :: Python :: 3.10
Classifier: Programming Language :: Python :: 3.11
Classifier: Programming Language :: Python :: 3.6
Classifier: Programming Language :: Python :: 3.7
Classifier: Programming Language :: Python :: 3.8
Classifier: Programming Language :: Python :: 3.9
Classifier: Programming Language :: Python :: Implementation :: CPython
Classifier: Programming Language :: Python :: Implementation :: PyPy
Classifier: Topic :: Other/Nonlisted Topic
Classifier: Topic :: Software Development :: Interpreters
Classifier: Topic :: Software Development :: Libraries :: Python Modules
Requires-Python: >=3.6
Requires-Dist: antlr4-python3-runtime==4.11.1
Requires-Dist: dataclasses==0.8; python_version == '3.6'
